casambi/__init__.py
casambi/__main__.py
casambi-0.165.dist-info/LICENSE.txt
casambi-0.165.dist-info/METADATA
casambi-0.165.dist-info/WHEEL
casambi-0.165.dist-info/top_level.txt
casambi-0.165.dist-info/RECORD
