Metadata-Version: 2.1
Name: casambi
Version: 0.165
Summary: Library to control Casambi light through cloudapi
Home-page: https://github.com/hellqvio86/casambi
Author: Olof Hellqvist
Author-email: olof.hellqvist@gmail.com
License: MIT
Download-URL: https://github.com/hellqvio86/casambi/archive/v_01.tar.gz
Keywords: casambi,light
Platform: UNKNOWN
Classifier: Development Status :: 3 - Alpha
Classifier: Intended Audience :: Developers
Classifier: Topic :: Software Development :: Build Tools
Classifier: License :: OSI Approved :: MIT License
Classifier: Programming Language :: Python :: 3
Classifier: Programming Language :: Python :: 3.6
Requires-Python: >=3.6
License-File: LICENSE.txt
Requires-Dist: pyyaml
Requires-Dist: requests
Requires-Dist: websocket-client
Provides-Extra: tests
Requires-Dist: pyyaml ; extra == 'tests'
